robo_transformers/__init__.py
robo_transformers/abstract/__init__.py
robo_transformers/abstract/action.py
robo_transformers/abstract/agent.py
robo_transformers/demo.py
robo_transformers/demo_imgs/gripper_almost_grasp.png
robo_transformers/demo_imgs/gripper_far_from_grasp.png
robo_transformers/demo_imgs/gripper_mid_to_grasp.png
robo_transformers/inference_server.py
robo_transformers/models/octo/__init__.py
robo_transformers/models/octo/action.py
robo_transformers/models/octo/agent.py
robo_transformers/models/octo/inference.py
robo_transformers/models/rt1/__init__.py
robo_transformers/models/rt1/action.py
robo_transformers/models/rt1/agent.py
robo_transformers/models/rt1/inference.py
robo_transformers/registry.py
robo_transformers-1.0.0.dist-info/METADATA
robo_transformers-1.0.0.dist-info/WHEEL
robo_transformers-1.0.0.dist-info/RECORD
