Metadata-Version: 2.1
Name: robo-transformers
Version: 1.0.0
Summary: RT-1, RT-1-X, Octo Robotics Transformer Model Inference
License: MIT
Author: Sebastian Peralta
Author-email: peraltas@seas.upenn.edu
Requires-Python: >=3.9,<3.12
Classifier: License :: OSI Approved :: MIT License
Classifier: Programming Language :: Python :: 3
Classifier: Programming Language :: Python :: 3.9
Classifier: Programming Language :: Python :: 3.10
Classifier: Programming Language :: Python :: 3.11
Requires-Dist: beartype (>=0.16.4,<0.17.0)
Requires-Dist: distrax (>=0.1.5,<0.2.0)
Requires-Dist: einops (>=0.7.0,<0.8.0)
Requires-Dist: flax (>=0.7.5,<0.8.0)
Requires-Dist: gdown (>=4.7.1,<5.0.0)
Requires-Dist: huggingface-hub (>=0.20.2,<0.21.0)
Requires-Dist: importlib-resources (>=6.1.1,<7.0.0)
Requires-Dist: jax (>=0.4.23,<0.5.0)
Requires-Dist: jaxlib (>=0.4.23,<0.5.0)
Requires-Dist: lark (>=1.1.9,<2.0.0)
Requires-Dist: opencv-python (>=4.9.0.80,<5.0.0.0)
Requires-Dist: pillow (>=10.1.0,<11.0.0)
Requires-Dist: protobuf (>=3.19.6,<4.24)
Requires-Dist: pyyaml (>=6.0.1,<7.0.0)
Requires-Dist: tensorflow (>=2.15.0,<3.0.0)
Requires-Dist: tensorflow-hub (>=0.15.0,<0.16.0)
Requires-Dist: tf-agents (>=0.19.0,<0.20.0)
Requires-Dist: transformers (>=4.36.2,<5.0.0)
